user/src/ton.v
module ton(
    input clk,
    input rst_n,
    input set,
    output reg reset_pwm
);

parameter ton_time = 40;
parameter conuter_width = 21;
reg [conuter_width-1:0] counter;

localparam IDLE = 3'd0;
localparam UP =   3'd1;

reg [2:0] state,state_next;

wire counter_ton = (counter == ton_time);
reg set_dly;
wire set_pos = (~set_dly) & set;

always @(posedge clk or negedge rst_n)
begin
    if(!rst_n)
    begin
        set_dly <= 0;
    end
    else
    begin
        set_dly <= set;
    end
end

// 三段式状态机，状态转换
always @(posedge clk or negedge rst_n)
begin
    if(!rst_n)
    begin
        state <= IDLE;
    end
    else
    begin
        state <= state_next;
    end
end

// 三段式状态机，下一状态赋值
always @(*)
begin
    case(state)
        3'd0:state_next <= set_pos?UP:IDLE;
        3'd1:state_next <= counter_ton?IDLE:UP;
        default: state_next <= IDLE;
    endcase
end

always @(posedge clk or negedge rst_n)
begin
    if(!rst_n)
    begin
        counter <= 0;
    end
    else
    begin
        case(state)
            IDLE:   counter <= 0;
            UP:     counter <= counter+1;
            default:counter <= 0;
        endcase
    end
end

// 输出reset赋值
always @(*)
begin
    if(counter_ton)
    begin
        reset_pwm <= 1;
    end
    else
    begin
        reset_pwm <= 0;
    end
end

endmodule

user/sim/test_ton/testbench.v
`include "../../src/ton.v"

module testbench();

parameter DATA_WIDTH = 32;
parameter ADDR_WIDTH = 32;
parameter MAIN_FRE   = 100; //unit MHz
reg                   clk = 0;
reg                   rst_n = 0;

reg set = 0;

always begin
    #(500/MAIN_FRE) clk = ~clk;
end

always begin
    #50 rst_n = 1;
end
always begin
    #100 set = 1;
    #110 set = 0;
    #200 set = 1;
    #210 set = 0;
    #2000 set = 1;
end

//Instance 
// outports wire
wire   	reset_pwm;

ton u_ton(
	.clk       	( clk        ),
	.rst_n     	( rst_n      ),
	.set       	( set        ),
	.reset_pwm 	( reset_pwm  )
);



initial begin            
    $dumpfile("wave.vcd");        
    $dumpvars(0, testbench);    
    #50000 $finish;
end

endmodule  //TOP

user/sim/test_ton/wave.vcd
$date
	Sun Aug 27 15:27:55 2023
$end
$version
	Icarus Verilog
$end
$timescale
	1s
$end
$scope module testbench $end
$var wire 1 ! reset_pwm $end
$var parameter 32 " ADDR_WIDTH $end
$var parameter 32 # DATA_WIDTH $end
$var parameter 32 $ MAIN_FRE $end
$var reg 1 % clk $end
$var reg 1 & rst_n $end
$var reg 1 ' set $end
$scope module u_ton $end
$var wire 1 % clk $end
$var wire 1 & rst_n $end
$var wire 1 ' set $end
$var wire 1 ( set_pos $end
$var wire 1 ) counter_ton $end
$var parameter 3 * IDLE $end
$var parameter 3 + UP $end
$var parameter 32 , conuter_width $end
$var parameter 32 - ton_time $end
$var reg 21 . counter [20:0] $end
$var reg 1 ! reset_pwm $end
$var reg 1 / set_dly $end
$var reg 3 0 state [2:0] $end
$var reg 3 1 state_next [2:0] $end
$upscope $end
$upscope $end
$enddefinitions $end
$comment Show the parameter values. $end
$dumpall
b101000 -
b10101 ,
b1 +
b0 *
b1100100 $
b100000 #
b100000 "
$end
#0
$dumpvars
b0 1
b0 0
0/
b0 .
0)
0(
0'
0&
0%
0!
$end
#5
1%
#10
0%
#15
1%
#20
0%
#25
1%
#30
0%
#35
1%
#40
0%
#45
1%
#50
0%
1&
#55
1%
#60
0%
#65
1%
#70
0%
#75
1%
#80
0%
#85
1%
#90
0%
#95
1%
#100
b1 1
1(
0%
1'
#105
0(
b1 0
1/
1%
#110
0%
#115
b1 .
1%
#120
0%
#125
b10 .
1%
#130
0%
#135
b11 .
1%
#140
0%
#145
b100 .
1%
#150
0%
#155
b101 .
1%
#160
0%
#165
b110 .
1%
#170
0%
#175
b111 .
1%
#180
0%
#185
b1000 .
1%
#190
0%
#195
b1001 .
1%
#200
0%
#205
b1010 .
1%
#210
0%
0'
#215
0/
b1011 .
1%
#220
0%
#225
b1100 .
1%
#230
0%
#235
b1101 .
1%
#240
0%
#245
b1110 .
1%
#250
0%
#255
b1111 .
1%
#260
0%
#265
b10000 .
1%
#270
0%
#275
b10001 .
1%
#280
0%
#285
b10010 .
1%
#290
0%
#295
b10011 .
1%
#300
0%
#305
b10100 .
1%
#310
0%
#315
b10101 .
1%
#320
0%
#325
b10110 .
1%
#330
0%
#335
b10111 .
1%
#340
0%
#345
b11000 .
1%
#350
0%
#355
b11001 .
1%
#360
0%
#365
b11010 .
1%
#370
0%
#375
b11011 .
1%
#380
0%
#385
b11100 .
1%
#390
0%
#395
b11101 .
1%
#400
0%
#405
b11110 .
1%
#410
1(
0%
1'
#415
0(
1/
b11111 .
1%
#420
0%
#425
b100000 .
1%
#430
0%
#435
b100001 .
1%
#440
0%
#445
b100010 .
1%
#450
0%
#455
b100011 .
1%
#460
0%
#465
b100100 .
1%
#470
0%
#475
b100101 .
1%
#480
0%
#485
b100110 .
1%
#490
0%
#495
b100111 .
1%
#500
0%
#505
1!
b0 1
1)
b101000 .
1%
#510
0%
#515
0!
b0 0
0)
b101001 .
1%
#520
0%
#525
b0 .
1%
#530
0%
#535
1%
#540
0%
#545
1%
#550
0%
#555
1%
#560
0%
#565
1%
#570
0%
#575
1%
#580
0%
#585
1%
#590
0%
#595
1%
#600
0%
#605
1%
#610
0%
#615
1%
#620
0%
0'
#625
0/
1%
