user/src/ton.v
module ton(
    input clk,
    input rst_n,
    input set,
    output reg reset_pwm
);

parameter ton_time = 40;
parameter conuter_width = 21;
reg [conuter_width-1:0] counter;

localparam IDLE = 3'd0;
localparam UP =   3'd1;

reg [2:0] state,state_next;

wire counter_ton = (counter == ton_time);
reg set_dly;
wire set_pos = (~set_dly) & set;

always @(posedge clk or negedge rst_n)
begin
    if(!rst_n)
    begin
        set_dly <= 0;
    end
    else
    begin
        set_dly <= set;
    end
end

// 三段式状态机，状态转换
always @(posedge clk or negedge rst_n)
begin
    if(!rst_n)
    begin
        state <= IDLE;
    end
    else
    begin
        state <= state_next;
    end
end

// 三段式状态机，下一状态赋值
always @(posedge clk or negedge rst_n)
begin
    if(!rst_n)
    begin
        state_next <= IDLE;
    end
    else
    begin
    case(state)
        3'd0:state_next <= set_pos?UP:IDLE;
        3'd1:state_next <= counter_ton?IDLE:UP;
        default: state_next <= IDLE;
    endcase
    end
end

always @(posedge clk or negedge rst_n)
begin
    if(!rst_n)
    begin
        counter <= 0;
    end
    else
    begin
        case(state)
            IDLE:   counter <= 0;
            UP:     counter <= counter+1;
            default:counter <= 0;
        endcase
    end
end

// 输出reset赋值
always @(posedge clk or negedge rst_n)
begin
    if(rst_n)
    begin
        reset_pwm <= 0;
    end
    else
    begin
        if(counter_ton)
        begin
            reset_pwm <= 1;
        end
        else
        begin
            reset_pwm <= 0;
        end
    end
end


endmodule

user/sim/testbench.v
module testbench();

parameter DATA_WIDTH = 32;
parameter ADDR_WIDTH = 32;
parameter MAIN_FRE   = 100; //unit MHz
reg                   sys_clk = 0;
reg                   sys_rst = 1;
reg [DATA_WIDTH-1:0]  data = 0;
reg [ADDR_WIDTH-1:0]  addr = 0;

always begin
    #(500/MAIN_FRE) sys_clk = ~sys_clk;
end

always begin
    #50 sys_rst = 0;
end

always @(posedge sys_clk) begin
    if (sys_rst) 
        addr = 0;
    else      
        addr = addr + 1;
end
always @(posedge sys_clk) begin
    if (sys_rst) 
        data = 0;
    else      
        data = data + 1;
end

//Instance 
// outports wire
wire   	reset_pwm;

ton u_ton(
	.clk       	( clk        ),
	.rst_n     	( rst_n      ),
	.set       	( set        ),
	.reset_pwm 	( reset_pwm  )
);



initial begin            
    $dumpfile("wave.vcd");        
    $dumpvars(0, testbench);    
    #50000 $finish;
end

endmodule  //TOP

user/sim/wave.vcd
$date
	Sun Aug 27 12:47:13 2023
$end
$version
	Icarus Verilog
$end
$timescale
	1s
$end
$scope module testbench $end
$var wire 1 ! clk $end
$var wire 1 " rst_n $end
$var wire 1 # set $end
$var wire 1 $ reset_pwm $end
$var parameter 32 % ADDR_WIDTH $end
$var parameter 32 & DATA_WIDTH $end
$var parameter 32 ' MAIN_FRE $end
$var reg 32 ( addr [31:0] $end
$var reg 32 ) data [31:0] $end
$var reg 1 * sys_clk $end
$var reg 1 + sys_rst $end
$scope module u_ton $end
$var wire 1 ! clk $end
$var wire 1 " rst_n $end
$var wire 1 # set $end
$var wire 1 , set_pos $end
$var wire 1 - counter_ton $end
$var parameter 3 . IDLE $end
$var parameter 3 / UP $end
$var parameter 32 0 conuter_width $end
$var parameter 32 1 ton_time $end
$var reg 21 2 counter [20:0] $end
$var reg 1 $ reset_pwm $end
$var reg 1 3 set_dly $end
$var reg 3 4 state [2:0] $end
$var reg 3 5 state_next [2:0] $end
$upscope $end
$upscope $end
$enddefinitions $end
$comment Show the parameter values. $end
$dumpall
b101000 1
b10101 0
b1 /
b0 .
b1100100 '
b100000 &
b100000 %
$end
#0
$dumpvars
bx 5
bx 4
x3
bx 2
x-
x,
1+
0*
b0 )
b0 (
x$
z#
z"
z!
$end
#5
1*
#10
0*
#15
1*
#20
0*
#25
1*
#30
0*
#35
1*
#40
0*
#45
1*
#50
0*
0+
#55
b1 )
b1 (
1*
#60
0*
#65
b10 (
b10 )
1*
#70
0*
#75
b11 )
b11 (
1*
#80
0*
#85
b100 (
b100 )
1*
#90
0*
#95
b101 )
b101 (
1*
#100
0*
#105
b110 (
b110 )
1*
#110
0*
#115
b111 )
b111 (
1*
#120
0*
#125
b1000 (
b1000 )
1*
#130
0*
#135
b1001 )
b1001 (
1*
#140
0*
#145
b1010 (
b1010 )
1*
#150
0*
#155
b1011 )
b1011 (
1*
#160
0*
#165
b1100 (
b1100 )
1*
#170
0*
#175
b1101 )
b1101 (
1*
#180
0*
#185
b1110 (
b1110 )
1*
#190
0*
#195
b1111 )
b1111 (
1*
#200
0*
#205
b10000 (
b10000 )
1*
#210
0*
#215
b10001 )
b10001 (
1*
#220
0*
#225
b10010 (
b10010 )
1*
#230
0*
#235
b10011 )
b10011 (
1*
#240
0*
#245
b10100 (
b10100 )
1*
#250
0*
#255
b10101 )
b10101 (
1*
#260
0*
#265
b10110 (
b10110 )
1*
#270
0*
#275
b10111 )
b10111 (
1*
#280
0*
#285
b11000 (
b11000 )
1*
#290
0*
#295
b11001 )
b11001 (
1*
#300
0*
#305
b11010 (
b11010 )
1*
#310
0*
#315
b11011 )
b11011 (
1*
#320
0*
#325
b11100 (
b11100 )
1*
#330
0*
#335
b11101 )
b11101 (
1*
#340
0*
#345
b11110 (
b11110 )
1*
#350
0*
#355
b11111 )
b11111 (
1*
#360
0*
#365
b100000 (
b100000 )
1*
#370
0*
#375
b100001 )
b100001 (
1*
#380
0*
#385
b100010 (
b100010 )
1*
#390
0*
#395
b100011 )
b100011 (
1*
#400
0*
#405
b100100 (
b100100 )
1*
#410
0*
#415
b100101 )
b100101 (
1*
#420
0*
#425
b100110 (
b100110 )
1*
#430
0*
#435
b100111 )
b100111 (
1*
#440
0*
#445
b101000 (
b101000 )
1*
#450
0*
#455
b101001 )
b101001 (
1*
#460
0*
#465
b101010 (
b101010 )
1*
#470
0*
#475
b101011 )
b101011 (
1*
#480
0*
#485
b101100 (
b101100 )
1*
#490
0*
#495
b101101 )
b101101 (
1*
#500
0*
#505
b101110 (
b101110 )
1*
#510
0*
#515
b101111 )
b101111 (
1*
#520
0*
#525
b110000 (
b110000 )
1*
#530
0*
#535
b110001 )
b110001 (
1*
#540
0*
#545
b110010 (
b110010 )
1*
#550
0*
#555
b110011 )
b110011 (
1*
#560
0*
#565
b110100 (
b110100 )
1*
#570
0*
#575
b110101 )
b110101 (
1*
#580
0*
#585
b110110 (
b110110 )
1*
#590
0*
#595
b110111 )
b110111 (
1*
#600
0*
#605
b111000 (
b111000 )
1*
#610
0*
#615
b111001 )
b111001 (
1*
#620
0*
#625
b111010 (
b111010 )
1*
#630
0*
#635
b111011 )
b111011 (
1*
#640
0*
#645
b111100 (
b111100 )
1*
#650
0*
#655
b111101 )
b111101 (
1*
#660
0*
#665
b111110 (
b111110 )
1*
#670
0*
#675
b111111 )
b111111 (
1*
#680
0*
#685
b1000000 (
b1000000 )
1*
#690
0*
#695
b1000001 )
b1000001 (
1*
#700
0*
#705
b1000010 (
b1000010 )
1*
#710
0*
#715
b1000011 )
b1000011 (
1*
#720
0*
#725
b1000100 (
b1000100 )
1*
#730
0*
#735
b1000101 )
b1000101 (
1*
#740
0*
#745
b1000110 (
b1000110 )
1*
#750
0*
#755
b1000111 )
b1000111 (
1*
#760
0*
#765
b1001000 (
b1001000 )
1*
#770
0*
#775
b1001001 )
b1001001 (
1*
#780
0*
#785
b1001010 (
b1001010 )
1*
#790
0*
#795
b1001011 )
b1001011 (
1*
#800
0*
#805
b1001100 (
b1001100 )
1*
#810
0*
#815
b1001101 )
b1001101 (
1*
#820
0*
#825
b1001110 (
b1001110 )
1*
#830
0*
#835
b1001111 )
b1001111 (
1*
#840
0*
#845
b1010000 (
b1010000 )
1*
#850
0*
#855
b1010001 )
b1010001 (
1*
#860
0*
#865
b1010010 (
b1010010 )
1*
#870
0*
#875
b1010011 )
b1010011 (
1*
#880
0*
#885
b1010100 (
b1010100 )
1*
#890
0*
#895
b1010101 )
b1010101 (
1*
#900
0*
#905
b1010110 (
b1010110 )
1*
#910
0*
#915
b1010111 )
b1010111 (
1*
#920
0*
#925
b1011000 (
b1011000 )
1*
#930
0*
#935
b1011001 )
b1011001 (
1*
#940
0*
#945
b1011010 (
b1011010 )
1*
#950
0*
#955
b1011011 )
b1011011 (
1*
#960
0*
#965
b1011100 (
b1011100 )
1*
#970
0*
#975
b1011101 )
b1011101 (
1*
#980
0*
#985
b1011110 (
b1011110 )
1*
#990
0*
#995
b1011111 )
b1011111 (
1*
#1000
0*
#1005
b1100000 (
b1100000 )
1*
#1010
0*
#1015
b1100001 )
b1100001 (
1*
#1020
0*
#1025
b1100010 (
b1100010 )
1*
#1030
0*
#1035
b1100011 )
b1100011 (
1*
#1040
0*
#1045
b1100100 (
b1100100 )
1*
#1050
0*
#1055
b1100101 )
b1100101 (
1*
#1060
0*
#1065
b1100110 (
b1100110 )
1*
#1070
0*
#1075
b1100111 )
b1100111 (
1*
#1080
0*
#1085
b1101000 (
b1101000 )
1*
#1090
0*
#1095
b1101001 )
b1101001 (
1*
#1100
0*
#1105
b1101010 (
b1101010 )
1*
#1110
0*
#1115
b1101011 )
b1101011 (
1*
#1120
0*
#1125
b1101100 (
b1101100 )
1*
#1130
0*
#1135
b1101101 )
b1101101 (
1*
#1140
0*
#1145
b1101110 (
b1101110 )
1*
#1150
0*
#1155
b1101111 )
b1101111 (
1*
#1160
0*
#1165
b1110000 (
b1110000 )
1*
#1170
0*
#1175
b1110001 )
b1110001 (
1*
#1180
0*
#1185
b1110010 (
b1110010 )
1*
#1190
0*
#1195
b1110011 )
b1110011 (
1*
#1200
0*
#1205
b1110100 (
b1110100 )
1*
#1210
0*
#1215
b1110101 )
b1110101 (
1*
#1220
0*
#1225
b1110110 (
b1110110 )
1*
#1230
0*
#1235
b1110111 )
b1110111 (
1*
#1240
0*
#1245
b1111000 (
b1111000 )
1*
#1250
0*
#1255
b1111001 )
b1111001 (
1*
#1260
0*
#1265
b1111010 (
b1111010 )
1*
#1270
0*
#1275
b1111011 )
b1111011 (
1*
#1280
0*
#1285
b1111100 (
b1111100 )
1*
#1290
0*
#1295
b1111101 )
b1111101 (
1*
#1300
0*
#1305
b1111110 (
b1111110 )
1*
#1310
0*
#1315
b1111111 )
b1111111 (
1*
#1320
0*
#1325
b10000000 (
b10000000 )
1*
#1330
0*
#1335
b10000001 )
b10000001 (
1*
#1340
0*
#1345
b10000010 (
b10000010 )
1*
#1350
0*
#1355
b10000011 )
b10000011 (
1*
#1360
0*
#1365
b10000100 (
b10000100 )
1*
#1370
0*
#1375
b10000101 )
b10000101 (
1*
#1380
0*
#1385
b10000110 (
b10000110 )
1*
#1390
0*
#1395
b10000111 )
b10000111 (
1*
#1400
0*
#1405
b10001000 (
b10001000 )
1*
#1410
0*
#1415
b10001001 )
b10001001 (
1*
#1420
0*
#1425
b10001010 (
b10001010 )
1*
#1430
0*
#1435
b10001011 )
b10001011 (
1*
#1440
0*
#1445
b10001100 (
b10001100 )
1*
#1450
0*
#1455
b10001101 )
b10001101 (
1*
#1460
0*
#1465
b10001110 (
b10001110 )
1*
#1470
0*
#1475
b10001111 )
b10001111 (
1*
#1480
0*
#1485
b10010000 (
b10010000 )
1*
#1490
0*
#1495
b10010001 )
b10010001 (
1*
#1500
0*
#1505
b10010010 (
b10010010 )
1*
#1510
0*
#1515
b10010011 )
b10010011 (
1*
#1520
0*
#1525
b10010100 (
b10010100 )
1*
#1530
0*
#1535
b10010101 )
b10010101 (
1*
#1540
0*
#1545
b10010110 (
b10010110 )
1*
#1550
0*
#1555
b10010111 )
b10010111 (
1*
#1560
0*
#1565
b10011000 (
b10011000 )
1*
#1570
0*
#1575
b10011001 )
b10011001 (
1*
#1580
0*
#1585
b10011010 (
b10011010 )
1*
#1590
0*
#1595
b10011011 )
b10011011 (
1*
#1600
0*
#1605
b10011100 (
b10011100 )
1*
#1610
0*
#1615
b10011101 )
b10011101 (
1*
#1620
0*
#1625
b10011110 (
b10011110 )
1*
#1630
0*
#1635
b10011111 )
b10011111 (
1*
#1640
0*
#1645
b10100000 (
b10100000 )
1*
#1650
0*
#1655
b10100001 )
b10100001 (
1*
#1660
0*
#1665
b10100010 (
b10100010 )
1*
#1670
0*
#1675
b10100011 )
b10100011 (
1*
#1680
0*
#1685
b10100100 (
b10100100 )
1*
#1690
0*
#1695
b10100101 )
b10100101 (
1*
#1700
0*
#1705
b10100110 (
b10100110 )
1*
#1710
0*
#1715
b10100111 )
b10100111 (
1*
#1720
0*
#1725
b10101000 (
b10101000 )
1*
#1730
0*
#1735
b10101001 )
b10101001 (
1*
#1740
0*
#1745
b10101010 (
b10101010 )
1*
#1750
0*
#1755
b10101011 )
b10101011 (
1*
#1760
0*
#1765
b10101100 (
b10101100 )
1*
#1770
0*
#1775
b10101101 )
b10101101 (
1*
#1780
0*
#1785
b10101110 (
b10101110 )
1*
#1790
0*
#1795
b10101111 )
b10101111 (
1*
#1800
0*
#1805
b10110000 (
b10110000 )
1*
#1810
0*
#1815
b10110001 )
b10110001 (
1*
#1820
0*
#1825
b10110010 (
b10110010 )
1*
#1830
0*
#1835
b10110011 )
b10110011 (
1*
#1840
0*
#1845
b10110100 (
b10110100 )
1*
#1850
0*
#1855
b10110101 )
b10110101 (
1*
#1860
0*
#1865
b10110110 (
b10110110 )
1*
#1870
0*
#1875
b10110111 )
b10110111 (
1*
#1880
0*
#1885
b10111000 (
b10111000 )
1*
#1890
0*
#1895
b10111001 )
b10111001 (
1*
#1900
0*
#1905
b10111010 (
b10111010 )
1*
#1910
0*
#1915
b10111011 )
b10111011 (
1*
#1920
0*
#1925
b10111100 (
b10111100 )
1*
#1930
0*
#1935
b10111101 )
b10111101 (
1*
#1940
0*
#1945
b10111110 (
b10111110 )
1*
#1950
0*
#1955
b10111111 )
b10111111 (
1*
#1960
0*
#1965
b11000000 (
b11000000 )
1*
#1970
0*
#1975
b11000001 )
b11000001 (
1*
#1980
0*
#1985
b11000010 (
b11000010 )
1*
#1990
0*
#1995
b11000011 )
b11000011 (
1*
#2000
0*
#2005
b11000100 (
b11000100 )
1*
#2010
0*
#2015
b11000101 )
b11000101 (
1*
#2020
0*
#2025
b11000110 (
b11000110 )
1*
#2030
0*
#2035
b11000111 )
b11000111 (
1*
#2040
0*
#2045
b11001000 (
b11001000 )
1*
#2050
0*
#2055
b11001001 )
b11001001 (
1*
#2060
0*
#2065
b11001010 (
b11001010 )
1*
#2070
0*
#2075
b11001011 )
b11001011 (
1*
#2080
0*
#2085
b11001100 (
b11001100 )
1*
#2090
0*
#2095
b11001101 )
b11001101 (
1*
#2100
0*
#2105
b11001110 (
b11001110 )
1*
#2110
0*
#2115
b11001111 )
b11001111 (
1*
#2120
0*
#2125
b11010000 (
b11010000 )
1*
#2130
0*
#2135
b11010001 )
b11010001 (
1*
#2140
0*
#2145
b11010010 (
b11010010 )
1*
#2150
0*
#2155
b11010011 )
b11010011 (
1*
#2160
0*
#2165
b11010100 (
b11010100 )
1*
#2170
0*
#2175
b11010101 )
b11010101 (
1*
#2180
0*
#2185
b11010110 (
b11010110 )
1*
#2190
0*
#2195
b11010111 )
b11010111 (
1*
#2200
0*
#2205
b11011000 (
b11011000 )
1*
#2210
0*
#2215
b11011001 )
b11011001 (
1*
#2220
0*
#2225
b11011010 (
b11011010 )
1*
#2230
0*
#2235
b11011011 )
b11011011 (
1*
#2240
0*
#2245
b11011100 (
b11011100 )
1*
#2250
0*
#2255
b11011101 )
b11011101 (
1*
#2260
0*
#2265
b11011110 (
b11011110 )
1*
#2270
0*
#2275
b11011111 )
b11011111 (
1*
#2280
0*
#2285
b11100000 (
b11100000 )
1*
#2290
0*
#2295
b11100001 )
b11100001 (
1*
#2300
0*
#2305
b11100010 (
b11100010 )
1*
#2310
0*
#2315
b11100011 )
b11100011 (
1*
#2320
0*
#2325
b11100100 (
b11100100 )
1*
#2330
0*
#2335
b11100101 )
b11100101 (
1*
#2340
0*
#2345
b11100110 (
b11100110 )
1*
#2350
0*
#2355
b11100111 )
b11100111 (
1*
#2360
0*
#2365
b11101000 (
b11101000 )
1*
#2370
0*
#2375
b11101001 )
b11101001 (
1*
#2380
0*
#2385
b11101010 (
b11101010 )
1*
#2390
0*
#2395
b11101011 )
b11101011 (
1*
#2400
0*
#2405
b11101100 (
b11101100 )
1*
#2410
0*
#2415
b11101101 )
b11101101 (
1*
#2420
0*
#2425
b11101110 (
b11101110 )
1*
#2430
0*
#2435
b11101111 )
b11101111 (
1*
#2440
0*
#2445
b11110000 (
b11110000 )
1*
#2450
0*
#2455
b11110001 )
b11110001 (
1*
#2460
0*
#2465
b11110010 (
b11110010 )
1*
#2470
0*
#2475
b11110011 )
b11110011 (
1*
#2480
0*
#2485
b11110100 (
b11110100 )
1*
#2490
0*
#2495
b11110101 )
b11110101 (
1*
#2500
0*
#2505
b11110110 (
b11110110 )
1*
#2510
0*
#2515
b11110111 )
b11110111 (
1*
#2520
0*
#2525
b11111000 (
b11111000 )
1*
#2530
0*
#2535
b11111001 )
b11111001 (
1*
#2540
0*
#2545
b11111010 (
b11111010 )
1*
#2550
0*
#2555
b11111011 )
b11111011 (
1*
#2560
0*
#2565
b11111100 (
b11111100 )
1*
#2570
0*
#2575
b11111101 )
b11111101 (
1*
#2580
0*
#2585
b11111110 (
b11111110 )
1*
#2590
0*
#2595
b11111111 )
b11111111 (
1*
#2600
0*
#2605
b100000000 (
b100000000 )
1*
#2610
0*
#2615
b100000001 )
b100000001 (
1*
#2620
0*
#2625
b100000010 (
b100000010 )
1*
#2630
0*
#2635
b100000011 )
b100000011 (
1*
#2640
0*
#2645
b100000100 (
b100000100 )
1*
#2650
0*
#2655
b100000101 )
b100000101 (
1*
#2660
0*
#2665
b100000110 (
b100000110 )
1*
#2670
0*
#2675
b100000111 )
b100000111 (
1*
#2680
0*
#2685
b100001000 (
b100001000 )
1*
#2690
0*
#2695
b100001001 )
b100001001 (
1*
#2700
0*
#2705
b100001010 (
b100001010 )
1*
#2710
0*
#2715
b100001011 )
b100001011 (
1*
#2720
0*
#2725
b100001100 (
b100001100 )
1*
#2730
0*
#2735
b100001101 )
b100001101 (
1*
#2740
0*
#2745
b100001110 (
b100001110 )
1*
#2750
0*
#2755
b100001111 )
b100001111 (
1*
#2760
0*
#2765
b100010000 (
b100010000 )
1*
#2770
0*
#2775
b100010001 )
b100010001 (
1*
#2780
0*
#2785
b100010010 (
b100010010 )
1*
#2790
0*
#2795
b100010011 )
b100010011 (
1*
#2800
0*
#2805
b100010100 (
b100010100 )
1*
#2810
0*
#2815
b100010101 )
b100010101 (
1*
#2820
0*
#2825
b100010110 (
b100010110 )
1*
#2830
0*
#2835
b100010111 )
b100010111 (
1*
#2840
0*
#2845
b100011000 (
b100011000 )
1*
#2850
0*
#2855
b100011001 )
b100011001 (
1*
#2860
0*
#2865
b100011010 (
b100011010 )
1*
#2870
0*
#2875
b100011011 )
b100011011 (
1*
#2880
0*
#2885
b100011100 (
b100011100 )
1*
#2890
0*
#2895
b100011101 )
b100011101 (
1*
#2900
0*
#2905
b100011110 (
b100011110 )
1*
#2910
0*
#2915
b100011111 )
b100011111 (
1*
#2920
0*
#2925
b100100000 (
b100100000 )
1*
#2930
0*
#2935
b100100001 )
b100100001 (
1*
#2940
0*
#2945
b100100010 (
b100100010 )
1*
#2950
0*
#2955
b100100011 )
b100100011 (
1*
#2960
0*
#2965
b100100100 (
b100100100 )
1*
#2970
0*
#2975
b100100101 )
b100100101 (
1*
#2980
0*
#2985
b100100110 (
b100100110 )
1*
#2990
0*
#2995
b100100111 )
b100100111 (
1*
#3000
0*
#3005
b100101000 (
b100101000 )
1*
#3010
0*
#3015
b100101001 )
b100101001 (
1*
#3020
0*
#3025
b100101010 (
b100101010 )
1*
#3030
0*
#3035
b100101011 )
b100101011 (
1*
#3040
0*
#3045
b100101100 (
b100101100 )
1*
#3050
0*
#3055
b100101101 )
b100101101 (
1*
#3060
0*
#3065
b100101110 (
b100101110 )
1*
#3070
0*
#3075
b100101111 )
b100101111 (
1*
#3080
0*
#3085
b100110000 (
b100110000 )
1*
#3090
0*
#3095
b100110001 )
b100110001 (
1*
#3100
0*
#3105
b100110010 (
b100110010 )
1*
#3110
0*
#3115
b100110011 )
b100110011 (
1*
#3120
0*
#3125
b100110100 (
b100110100 )
1*
#3130
0*
#3135
b100110101 )
b100110101 (
1*
#3140
0*
#3145
b100110110 (
b100110110 )
1*
#3150
0*
#3155
b100110111 )
b100110111 (
1*
#3160
0*
#3165
b100111000 (
b100111000 )
1*
#3170
0*
#3175
b100111001 )
b100111001 (
1*
#3180
0*
#3185
b100111010 (
b100111010 )
1*
#3190
0*
#3195
b100111011 )
b100111011 (
1*
#3200
0*
#3205
b100111100 (
b100111100 )
1*
#3210
0*
#3215
b100111101 )
b100111101 (
1*
#3220
0*
#3225
b100111110 (
b100111110 )
1*
#3230
0*
#3235
b100111111 )
b100111111 (
1*
#3240
0*
#3245
b101000000 (
b101000000 )
1*
#3250
0*
#3255
b101000001 )
b101000001 (
1*
#3260
0*
#3265
b101000010 (
b101000010 )
1*
#3270
0*
#3275
b101000011 )
b101000011 (
1*
#3280
0*
#3285
b101000100 (
b101000100 )
1*
#3290
0*
#3295
b101000101 )
b101000101 (
1*
#3300
0*
#3305
b101000110 (
b101000110 )
1*
#3310
0*
#3315
b101000111 )
b101000111 (
1*
#3320
0*
#3325
b101001000 (
b101001000 )
1*
#3330
0*
#3335
b101001001 )
b101001001 (
1*
#3340
0*
#3345
b101001010 (
b101001010 )
1*
#3350
0*
#3355
b101001011 )
b101001011 (
1*
#3360
0*
#3365
b101001100 (
b101001100 )
1*
#3370
0*
#3375
b101001101 )
b101001101 (
1*
#3380
0*
#3385
b101001110 (
b101001110 )
1*
#3390
0*
#3395
b101001111 )
b101001111 (
1*
#3400
0*
#3405
b101010000 (
b101010000 )
1*
#3410
0*
#3415
b101010001 )
b101010001 (
1*
#3420
0*
#3425
b101010010 (
b101010010 )
1*
#3430
0*
#3435
b101010011 )
b101010011 (
1*
#3440
0*
#3445
b101010100 (
b101010100 )
1*
#3450
0*
#3455
b101010101 )
b101010101 (
1*
#3460
0*
#3465
b101010110 (
b101010110 )
1*
#3470
0*
#3475
b101010111 )
b101010111 (
1*
#3480
0*
#3485
b101011000 (
b101011000 )
1*
#3490
0*
#3495
b101011001 )
b101011001 (
1*
#3500
0*
#3505
b101011010 (
b101011010 )
1*
#3510
0*
#3515
b101011011 )
b101011011 (
1*
#3520
0*
#3525
b101011100 (
b101011100 )
1*
#3530
0*
#3535
b101011101 )
b101011101 (
1*
#3540
0*
#3545
b101011110 (
b101011110 )
1*
#3550
0*
#3555
b101011111 )
b101011111 (
1*
#3560
0*
#3565
b101100000 (
b101100000 )
1*
#3570
0*
#3575
b101100001 )
b101100001 (
1*
#3580
0*
#3585
b101100010 (
b101100010 )
1*
#3590
0*
#3595
b101100011 )
b101100011 (
1*
#3600
0*
#3605
b101100100 (
b101100100 )
1*
#3610
0*
#3615
b101100101 )
b101100101 (
1*
#3620
0*
#3625
b101100110 (
b101100110 )
1*
#3630
0*
#3635
b101100111 )
b101100111 (
1*
#3640
0*
#3645
b101101000 (
b101101000 )
1*
#3650
0*
#3655
b101101001 )
b101101001 (
1*
#3660
0*
#3665
b101101010 (
b101101010 )
1*
#3670
0*
#3675
b101101011 )
b101101011 (
1*
#3680
0*
#3685
b101101100 (
b101101100 )
1*
#3690
0*
#3695
b101101101 )
b101101101 (
1*
#3700
0*
#3705
b101101110 (
b101101110 )
1*
#3710
0*
#3715
b101101111 )
b101101111 (
1*
#3720
0*
#3725
b101110000 (
b101110000 )
1*
#3730
0*
#3735
b101110001 )
b101110001 (
1*
#3740
0*
#3745
b101110010 (
b101110010 )
1*
#3750
0*
#3755
b101110011 )
b101110011 (
1*
#3760
0*
#3765
b101110100 (
b101110100 )
1*
#3770
0*
#3775
b101110101 )
b101110101 (
1*
#3780
0*
#3785
b101110110 (
b101110110 )
1*
#3790
0*
#3795
b101110111 )
b101110111 (
1*
#3800
0*
#3805
b101111000 (
b101111000 )
1*
#3810
0*
#3815
b101111001 )
b101111001 (
1*
#3820
0*
#3825
b101111010 (
b101111010 )
1*
#3830
0*
#3835
b101111011 )
b101111011 (
1*
#3840
0*
#3845
b101111100 (
b101111100 )
1*
#3850
0*
#3855
b101111101 )
b101111101 (
1*
#3860
0*
#3865
b101111110 (
b101111110 )
1*
#3870
0*
#3875
b101111111 )
b101111111 (
1*
#3880
0*
#3885
b110000000 (
b110000000 )
1*
#3890
0*
#3895
b110000001 )
b110000001 (
1*
#3900
0*
#3905
b110000010 (
b110000010 )
1*
#3910
0*
#3915
b110000011 )
b110000011 (
1*
#3920
0*
#3925
b110000100 (
b110000100 )
1*
#3930
0*
#3935
b110000101 )
b110000101 (
1*
#3940
0*
#3945
b110000110 (
b110000110 )
1*
#3950
0*
#3955
b110000111 )
b110000111 (
1*
#3960
0*
#3965
b110001000 (
b110001000 )
1*
#3970
0*
#3975
b110001001 )
b110001001 (
1*
#3980
0*
#3985
b110001010 (
b110001010 )
1*
#3990
0*
#3995
b110001011 )
b110001011 (
1*
#4000
0*
#4005
b110001100 (
b110001100 )
1*
#4010
0*
#4015
b110001101 )
b110001101 (
1*
#4020
0*
#4025
b110001110 (
b110001110 )
1*
#4030
0*
#4035
b110001111 )
b110001111 (
1*
#4040
0*
#4045
b110010000 (
b110010000 )
1*
#4050
0*
#4055
b110010001 )
b110010001 (
1*
#4060
0*
#4065
b110010010 (
b110010010 )
1*
#4070
0*
#4075
b110010011 )
b110010011 (
1*
#4080
0*
#4085
b110010100 (
b110010100 )
1*
#4090
0*
#4095
b110010101 )
b110010101 (
1*
#4100
0*
#4105
b110010110 (
b110010110 )
1*
#4110
0*
#4115
b110010111 )
b110010111 (
1*
#4120
0*
#4125
b110011000 (
b110011000 )
1*
#4130
0*
#4135
b110011001 )
b110011001 (
1*
#4140
0*
#4145
b110011010 (
b110011010 )
1*
#4150
0*
#4155
b110011011 )
b110011011 (
1*
#4160
0*
#4165
b110011100 (
b110011100 )
1*
#4170
0*
#4175
b110011101 )
b110011101 (
1*
#4180
0*
#4185
b110011110 (
b110011110 )
1*
#4190
0*
#4195
b110011111 )
b110011111 (
1*
#4200
0*
#4205
b110100000 (
b110100000 )
1*
#4210
0*
#4215
b110100001 )
b110100001 (
1*
#4220
0*
#4225
b110100010 (
b110100010 )
1*
#4230
0*
#4235
b110100011 )
b110100011 (
1*
#4240
0*
#4245
b110100100 (
b110100100 )
1*
#4250
0*
#4255
b110100101 )
b110100101 (
1*
#4260
0*
#4265
b110100110 (
b110100110 )
1*
#4270
0*
#4275
b110100111 )
b110100111 (
1*
#4280
0*
#4285
b110101000 (
b110101000 )
1*
#4290
0*
#4295
b110101001 )
b110101001 (
1*
#4300
0*
#4305
b110101010 (
b110101010 )
1*
#4310
0*
#4315
b110101011 )
b110101011 (
1*
#4320
0*
#4325
b110101100 (
b110101100 )
1*
#4330
0*
#4335
b110101101 )
b110101101 (
1*
#4340
0*
#4345
b110101110 (
b110101110 )
1*
#4350
0*
#4355
b110101111 )
b110101111 (
1*
#4360
0*
#4365
b110110000 (
b110110000 )
1*
#4370
0*
#4375
b110110001 )
b110110001 (
1*
#4380
0*
#4385
b110110010 (
b110110010 )
1*
#4390
0*
#4395
b110110011 )
b110110011 (
1*
#4400
0*
#4405
b110110100 (
b110110100 )
1*
#4410
0*
#4415
b110110101 )
b110110101 (
1*
#4420
0*
#4425
b110110110 (
b110110110 )
1*
#4430
0*
#4435
b110110111 )
b110110111 (
1*
#4440
0*
#4445
b110111000 (
b110111000 )
1*
#4450
0*
#4455
b110111001 )
b110111001 (
1*
#4460
0*
#4465
b110111010 (
b110111010 )
1*
#4470
0*
#4475
b110111011 )
b110111011 (
1*
#4480
0*
#4485
b110111100 (
b110111100 )
1*
#4490
0*
#4495
b110111101 )
b110111101 (
1*
#4500
0*
#4505
b110111110 (
b110111110 )
1*
#4510
0*
#4515
b110111111 )
b110111111 (
1*
#4520
0*
#4525
b111000000 (
b111000000 )
1*
#4530
0*
#4535
b111000001 )
b111000001 (
1*
#4540
0*
#4545
b111000010 (
b111000010 )
1*
#4550
0*
#4555
b111000011 )
b111000011 (
1*
#4560
0*
#4565
b111000100 (
b111000100 )
1*
#4570
0*
#4575
b111000101 )
b111000101 (
1*
#4580
0*
#4585
b111000110 (
b111000110 )
1*
#4590
0*
#4595
b111000111 )
b111000111 (
1*
#4600
0*
#4605
b111001000 (
b111001000 )
1*
#4610
0*
#4615
b111001001 )
b111001001 (
1*
#4620
0*
#4625
b111001010 (
b111001010 )
1*
#4630
0*
#4635
b111001011 )
b111001011 (
1*
#4640
0*
#4645
b111001100 (
b111001100 )
1*
#4650
0*
#4655
b111001101 )
b111001101 (
1*
#4660
0*
#4665
b111001110 (
b111001110 )
1*
#4670
0*
#4675
b111001111 )
b111001111 (
1*
#4680
0*
#4685
b111010000 (
b111010000 )
1*
#4690
0*
#4695
b111010001 )
b111010001 (
1*
#4700
0*
#4705
b111010010 (
b111010010 )
1*
#4710
0*
#4715
b111010011 )
b111010011 (
1*
#4720
0*
#4725
b111010100 (
b111010100 )
1*
#4730
0*
#4735
b111010101 )
b111010101 (
1*
#4740
0*
#4745
b111010110 (
b111010110 )
1*
#4750
0*
#4755
b111010111 )
b111010111 (
1*
#4760
0*
#4765
b111011000 (
b111011000 )
1*
#4770
0*
#4775
b111011001 )
b111011001 (
1*
#4780
0*
#4785
b111011010 (
b111011010 )
1*
#4790
0*
#4795
b111011011 )
b111011011 (
1*
#4800
0*
#4805
b111011100 (
b111011100 )
1*
#4810
0*
#4815
b111011101 )
b111011101 (
1*
#4820
0*
#4825
b111011110 (
b111011110 )
1*
#4830
0*
#4835
b111011111 )
b111011111 (
1*
#4840
0*
