user/src/test_counter.v
`timescale 1ns/1ps
module test_counter ();

    localparam TEST_WIDTH = 6;
    localparam TEST_MAX   = 9;
    localparam CLK_PERIOD = 10;

    reg clk = 1'b1; // 时钟

    wire [TEST_WIDTH-1:0] cnt;

    counter #( // 参数例化
        .CNT_WIDTH (TEST_WIDTH),
        .CNT_INIT  (3),
        .CNT_MAX   (TEST_MAX)
    ) uut ( // 端口例化
        .clk       (clk),
        .cnt       (cnt)
    );

    always #(CLK_PERIOD/2) clk = ~clk; // 50MHz

    always @ (posedge clk) begin
        $display("time : %8t , counter = %d", $time, cnt);
        if (cnt == TEST_MAX)
            $display("time : %8t , counter overflow", $time);
        else if (cnt == 0)
            $display("hello world");
    end
    initial begin
        $dumpfile("test_counter.vcd");
        $dumpvars(0, test_counter); // dump所有信号波形
    end 

    initial begin // 第3次计数值为2后退出仿真
        repeat(3) begin
            wait (cnt == 2);
            #(CLK_PERIOD);
        end

        $finish;
    end

endmodule

module counter #( // 参数
    parameter CNT_WIDTH = 8,
    parameter CNT_INIT = 0,
    parameter CNT_MAX = 11
) ( // 端口
    input clk,
    output reg [CNT_WIDTH-1:0] cnt
);

    initial cnt = CNT_INIT;

    always @ (posedge clk)
        if(cnt < CNT_MAX)
            cnt <= cnt + 1;
        else
            cnt <= 0;

endmodule

user/src/test_counter.vcd
$date
	Sat Aug 26 10:42:09 2023
$end
$version
	Icarus Verilog
$end
$timescale
	1ps
$end
$scope module test_counter $end
$var wire 6 ! cnt [5:0] $end
$var parameter 32 " CLK_PERIOD $end
$var parameter 32 # TEST_MAX $end
$var parameter 32 $ TEST_WIDTH $end
$var reg 1 % clk $end
$scope module uut $end
$var wire 1 % clk $end
$var parameter 32 & CNT_INIT $end
$var parameter 32 ' CNT_MAX $end
$var parameter 32 ( CNT_WIDTH $end
$var reg 6 ) cnt [5:0] $end
$upscope $end
$upscope $end
$enddefinitions $end
$comment Show the parameter values. $end
$dumpall
b110 (
b1001 '
b11 &
b110 $
b1001 #
b1010 "
$end
#0
$dumpvars
b100 )
1%
b100 !
$end
#5000
0%
#10000
b101 !
b101 )
1%
#15000
0%
#20000
b110 !
b110 )
1%
#25000
0%
#30000
b111 !
b111 )
1%
#35000
0%
#40000
b1000 !
b1000 )
1%
#45000
0%
#50000
b1001 !
b1001 )
1%
#55000
0%
#60000
b0 !
b0 )
1%
#65000
0%
#70000
b1 !
b1 )
1%
#75000
0%
#80000
b10 !
b10 )
1%
#85000
0%
#90000
b11 !
b11 )
1%
#95000
0%
#100000
b100 !
b100 )
1%
#105000
0%
#110000
b101 !
b101 )
1%
#115000
0%
#120000
b110 !
b110 )
1%
#125000
0%
#130000
b111 !
b111 )
1%
#135000
0%
#140000
b1000 !
b1000 )
1%
#145000
0%
#150000
b1001 !
b1001 )
1%
#155000
0%
#160000
b0 !
b0 )
1%
#165000
0%
#170000
b1 !
b1 )
1%
#175000
0%
#180000
b10 !
b10 )
1%
#185000
0%
#190000
b11 !
b11 )
1%
